[
  {
    "originalname": "Interview Questions .pdf",
    "filename": "Interview Questions (1).pdf",
    "url": "http://localhost:5000/uploads/Interview Questions (1).pdf"
  },
  {
    "originalname": "Interview Questions .docx",
    "filename": "Interview Questions .pdf",
    "url": "http://localhost:5000/uploads/Interview Questions .pdf"
  },
  {
    "originalname": "Interview Questions .docx",
    "filename": "Interview Questions (3).pdf",
    "url": "http://localhost:5000/uploads/Interview Questions (3).pdf"
  },
  {
    "originalname": "Interview Questions .pdf",
    "filename": "Interview Questions (4).pdf",
    "url": "http://localhost:5000/uploads/Interview Questions (4).pdf"
  },
  {
    "originalname": "Interview Questions .pdf",
    "filename": "Interview Questions .pdf",
    "url": "http://localhost:5000/uploads/Interview Questions .pdf"
  },
  {
    "originalname": "Interview Questions .docx",
    "filename": "Interview Questions .pdf",
    "url": "http://localhost:5000/uploads/Interview Questions .pdf"
  },
  {
    "originalname": "Interview Questions .pdf",
    "filename": "Interview Questions (1).pdf",
    "url": "http://localhost:5000/uploads/Interview Questions (1).pdf"
  },
  {
    "originalname": "Interview Questions .pdf",
    "filename": "Interview Questions .pdf",
    "url": "http://localhost:5000/uploads/Interview Questions .pdf"
  },
  {
    "originalname": "Interview Questions .pdf",
    "filename": "Interview Questions .pdf",
    "url": "http://localhost:5000/uploads/Interview Questions .pdf"
  }
]